graphs_darian303/__init__.py
graphs_darian303/heapq.py
graphs_darian303/sp.py
graphs_darian303-0.0.1.dist-info/METADATA
graphs_darian303-0.0.1.dist-info/WHEEL
graphs_darian303-0.0.1.dist-info/top_level.txt
graphs_darian303-0.0.1.dist-info/RECORD
