Metadata-Version: 2.4
Name: graphs_darian303
Version: 0.0.1
Summary: Python package implementing Dijkstra's algorithm
Author: Darian Dunn
Classifier: Programming Language :: Python :: 3
Classifier: Operating System :: OS Independent
Requires-Python: >=3.8
